<?xml version="1.0"?>
<manifest>
<file><filename>http://digfir-published.macmillanusa.com/strayersources3ehs/strayersources3ehs_ch14_1.html</filename><title>Author Preview Video with Robert Strayer for Chapter 14</title><id>56955d5a757a2e3036000000</id></file>
<file><filename>http://digfir-published.macmillanusa.com/strayersources3ehs/strayersources3ehs_ch14_1_dlap.xml</filename><title>DLAP questions</title><id>56955d5a757a2e3036000000</id></file>
<file><filename>http://digfir-published.macmillanusa.com/strayersources3ehs/strayersources3ehs_ch14_2.html</filename><title>Introduction to Chapter 14</title><id>56955d5a757a2e3036000000</id></file>
<file><filename>http://digfir-published.macmillanusa.com/strayersources3ehs/strayersources3ehs_ch14_2_dlap.xml</filename><title>DLAP questions</title><id>56955d5a757a2e3036000000</id></file>
<file><filename>http://digfir-published.macmillanusa.com/strayersources3ehs/strayersources3ehs_ch14_3.html</filename><title>Guided Reading Exercise for Chapter 14</title><id>56955d5a757a2e3036000000</id></file>
<file><filename>http://digfir-published.macmillanusa.com/strayersources3ehs/strayersources3ehs_ch14_3_dlap.xml</filename><title>DLAP questions</title><id>56955d5a757a2e3036000000</id></file>
<file><filename>http://digfir-published.macmillanusa.com/strayersources3ehs/strayersources3ehs_ch14_4.html</filename><title>Europeans and Asian Commerce
</title><id>56955d5a757a2e3036000000</id></file>
<file><filename>http://digfir-published.macmillanusa.com/strayersources3ehs/strayersources3ehs_ch14_4_dlap.xml</filename><title>DLAP questions</title><id>56955d5a757a2e3036000000</id></file>
<file><filename>http://digfir-published.macmillanusa.com/strayersources3ehs/strayersources3ehs_ch14_5.html</filename><title>A Portuguese Empire of Commerce
</title><id>56955d5a757a2e3036000000</id></file>
<file><filename>http://digfir-published.macmillanusa.com/strayersources3ehs/strayersources3ehs_ch14_5_dlap.xml</filename><title>DLAP questions</title><id>56955d5a757a2e3036000000</id></file>
<file><filename>http://digfir-published.macmillanusa.com/strayersources3ehs/strayersources3ehs_ch14_6.html</filename><title>Spain and the Philippines
</title><id>56955d5a757a2e3036000000</id></file>
<file><filename>http://digfir-published.macmillanusa.com/strayersources3ehs/strayersources3ehs_ch14_6_dlap.xml</filename><title>DLAP questions</title><id>56955d5a757a2e3036000000</id></file>
<file><filename>http://digfir-published.macmillanusa.com/strayersources3ehs/strayersources3ehs_ch14_7.html</filename><title>The East India Companies
</title><id>56955d5a757a2e3036000000</id></file>
<file><filename>http://digfir-published.macmillanusa.com/strayersources3ehs/strayersources3ehs_ch14_7_dlap.xml</filename><title>DLAP questions</title><id>56955d5a757a2e3036000000</id></file>
<file><filename>http://digfir-published.macmillanusa.com/strayersources3ehs/strayersources3ehs_ch14_8.html</filename><title>Asians and Asian Commerce
</title><id>56955d5a757a2e3036000000</id></file>
<file><filename>http://digfir-published.macmillanusa.com/strayersources3ehs/strayersources3ehs_ch14_8_dlap.xml</filename><title>DLAP questions</title><id>56955d5a757a2e3036000000</id></file>
<file><filename>http://digfir-published.macmillanusa.com/strayersources3ehs/strayersources3ehs_ch14_9.html</filename><title>Another Voice with Eric Nelson for Chapter 14</title><id>56955d5a757a2e3036000000</id></file>
<file><filename>http://digfir-published.macmillanusa.com/strayersources3ehs/strayersources3ehs_ch14_9_dlap.xml</filename><title>DLAP questions</title><id>56955d5a757a2e3036000000</id></file>
<file><filename>http://digfir-published.macmillanusa.com/strayersources3ehs/strayersources3ehs_ch14_10.html</filename><title>Silver and Global Commerce
</title><id>56955d5a757a2e3036000000</id></file>
<file><filename>http://digfir-published.macmillanusa.com/strayersources3ehs/strayersources3ehs_ch14_10_dlap.xml</filename><title>DLAP questions</title><id>56955d5a757a2e3036000000</id></file>
<file><filename>http://digfir-published.macmillanusa.com/strayersources3ehs/strayersources3ehs_ch14_11.html</filename><title>ZOOMING IN: Potosí, a Mountain of Silver</title><id>56955d5a757a2e3036000000</id></file>
<file><filename>http://digfir-published.macmillanusa.com/strayersources3ehs/strayersources3ehs_ch14_11_dlap.xml</filename><title>DLAP questions</title><id>56955d5a757a2e3036000000</id></file>
<file><filename>http://digfir-published.macmillanusa.com/strayersources3ehs/strayersources3ehs_ch14_12.html</filename><title>“The World Hunt”: Fur in Global Commerce
</title><id>56955d5a757a2e3036000000</id></file>
<file><filename>http://digfir-published.macmillanusa.com/strayersources3ehs/strayersources3ehs_ch14_12_dlap.xml</filename><title>DLAP questions</title><id>56955d5a757a2e3036000000</id></file>
<file><filename>http://digfir-published.macmillanusa.com/strayersources3ehs/strayersources3ehs_ch14_13.html</filename><title>Commerce in People: The Atlantic Slave Trade
</title><id>56955d5a757a2e3036000000</id></file>
<file><filename>http://digfir-published.macmillanusa.com/strayersources3ehs/strayersources3ehs_ch14_13_dlap.xml</filename><title>DLAP questions</title><id>56955d5a757a2e3036000000</id></file>
<file><filename>http://digfir-published.macmillanusa.com/strayersources3ehs/strayersources3ehs_ch14_14.html</filename><title>The Slave Trade in Context
</title><id>56955d5a757a2e3036000000</id></file>
<file><filename>http://digfir-published.macmillanusa.com/strayersources3ehs/strayersources3ehs_ch14_14_dlap.xml</filename><title>DLAP questions</title><id>56955d5a757a2e3036000000</id></file>
<file><filename>http://digfir-published.macmillanusa.com/strayersources3ehs/strayersources3ehs_ch14_15.html</filename><title>The Slave Trade in Practice
</title><id>56955d5a757a2e3036000000</id></file>
<file><filename>http://digfir-published.macmillanusa.com/strayersources3ehs/strayersources3ehs_ch14_15_dlap.xml</filename><title>DLAP questions</title><id>56955d5a757a2e3036000000</id></file>
<file><filename>http://digfir-published.macmillanusa.com/strayersources3ehs/strayersources3ehs_ch14_16.html</filename><title>Consequences: The Impact of the Slave Trade in Africa
</title><id>56955d5a757a2e3036000000</id></file>
<file><filename>http://digfir-published.macmillanusa.com/strayersources3ehs/strayersources3ehs_ch14_16_dlap.xml</filename><title>DLAP questions</title><id>56955d5a757a2e3036000000</id></file>
<file><filename>http://digfir-published.macmillanusa.com/strayersources3ehs/strayersources3ehs_ch14_17.html</filename><title>ZOOMING IN: Ayuba Suleiman Diallo: To Slavery and Back</title><id>56955d5a757a2e3036000000</id></file>
<file><filename>http://digfir-published.macmillanusa.com/strayersources3ehs/strayersources3ehs_ch14_17_dlap.xml</filename><title>DLAP questions</title><id>56955d5a757a2e3036000000</id></file>
<file><filename>http://digfir-published.macmillanusa.com/strayersources3ehs/strayersources3ehs_ch14_18.html</filename><title>REFLECTIONS: Economic Globalization — Then and Now
</title><id>56955d5a757a2e3036000000</id></file>
<file><filename>http://digfir-published.macmillanusa.com/strayersources3ehs/strayersources3ehs_ch14_18_dlap.xml</filename><title>DLAP questions</title><id>56955d5a757a2e3036000000</id></file>
<file><filename>http://digfir-published.macmillanusa.com/strayersources3ehs/strayersources3ehs_ch14_19.html</filename><title>What’s the Significance?
</title><id>56955d5a757a2e3036000000</id></file>
<file><filename>http://digfir-published.macmillanusa.com/strayersources3ehs/strayersources3ehs_ch14_19_dlap.xml</filename><title>DLAP questions</title><id>56955d5a757a2e3036000000</id></file>
<file><filename>http://digfir-published.macmillanusa.com/strayersources3ehs/strayersources3ehs_ch14_20.html</filename><title>Big Picture Questions
</title><id>56955d5a757a2e3036000000</id></file>
<file><filename>http://digfir-published.macmillanusa.com/strayersources3ehs/strayersources3ehs_ch14_20_dlap.xml</filename><title>DLAP questions</title><id>56955d5a757a2e3036000000</id></file>
<file><filename>http://digfir-published.macmillanusa.com/strayersources3ehs/strayersources3ehs_ch14_21.html</filename><title>Next Steps: For Further Study
</title><id>56955d5a757a2e3036000000</id></file>
<file><filename>http://digfir-published.macmillanusa.com/strayersources3ehs/strayersources3ehs_ch14_21_dlap.xml</filename><title>DLAP questions</title><id>56955d5a757a2e3036000000</id></file>
</manifest>